[{"@context":"http://schema.org/","@type":"Physician","name":"Frxc3xa9dxc3xa9ric LALYR","medicalSpecialty":"Ostxc3xa9opathe","legalName":null,"url":"/osteopathe/saint-etienne/frederic-lalyr","address":{"@type":"PostalAddress","name":"","streetAddress":"1 Rue Bourgneuf","postalCode":"42000","addressLocality":"Saint-xc3x89tienne"},"paymentAccepted":"Cash, Check"},{"@context":"http://schema.org/","@type":"Physician","name":"Cxc3xa9line Laffargue","medicalSpecialty":"Ostxc3xa9opathe","legalName":null,"url":"/osteopathe/mouthiers-sur-boeme/celine-laffargue","address":{"@type":"PostalAddress","name":"Cabinet mxc3xa9dical Bocage Villenave-d'Ornon","streetAddress":"16 Rue Colette Besson","postalCode":"33140","addressLocality":"Villenave-d'Ornon"},"paymentAccepted":"Cash, Check, Credit card"},{"@context":"http://schema.org/","@type":"Physician","name":"Serge ALFONSO","medicalSpecialty":"Ostxc3xa9opathe","legalName":null,"url":"/osteopathe/le-plessis-trevise/serge-alfonso","address":{"@type":"PostalAddress","name":"Maison mxc3xa9dicale du Plessis-Trxc3xa9vise","streetAddress":"1 bis avenue Ardouin","postalCode":"94420","addressLocality":"Le Plessis-Trxc3xa9vise"},"paymentAccepted":"Cash, Check, Credit card"},{"@context":"http://schema.org/","@type":"Physician","name":"Pierre AUBRY","medicalSpecialty":"Masseur-kinxc3xa9sithxc3xa9rapeute","legalName":null,"url":"/masseur-kinesitherapeute/charenton-le-pont/pierre-aubry-charenton-le-pont","address":{"@type":"PostalAddress","name":"Hxc3xb4pital Armand Brillard","streetAddress":"3-5 Avenue Watteau","postalCode":"94130","addressLocality":"Nogent-sur-Marne"},"paymentAccepted":"Cash, Check, Credit card"},{"@context":"http://schema.org/","@type":"Physician","name":"Clothilde Giraud","medicalSpecialty":"Ostxc3xa9opathe","legalName":null,"url":"/osteopathe/juvignac/clothilde-giraud","address":{"@type":"PostalAddress","name":"","streetAddress":"3 Rue Andrxc3xa9 Maurois","postalCode":"76500","addressLocality":"Elbeuf"},"paymentAccepted":"Cash, Check"},{"@context":"http://schema.org/","@type":"Physician","name":"Emmanuel Lainxc3xa9","medicalSpecialty":"Ostxc3xa9opathe","legalName":null,"url":"/osteopathe/paris/emmanuel-laine","address":{"@type":"PostalAddress","name":"Raspail","streetAddress":"17 Boulevard Raspail","postalCode":"75007","addressLocality":"Paris"},"paymentAccepted":"Cash, Credit card"},{"@context":"http://schema.org/","@type":"Physician","name":"Manon Bruyas","medicalSpecialty":"Ostxc3xa9opathe","legalName":null,"url":"/osteopathe/pralong/manon-bruyas","address":{"@type":"PostalAddress","name":"Cabinet d'ostxc3xa9opathie","streetAddress":"32 rue Louis Varigas","postalCode":"42600","addressLocality":"Pralong"},"paymentAccepted":"Cash, Check"},{"@context":"http://schema.org/","@type":"Physician","name":"Myrto Walter","medicalSpecialty":"Ostxc3xa9opathe","legalName":null,"url":"/osteopathe/paris/myrto-walter","address":{"@type":"PostalAddress","name":"GYNxc3x89Cxc3x89E PARIS","streetAddress":"62 Rue Blanche","postalCode":"75009","addressLocality":"Paris"},"paymentAccepted":"Cash, Check"},{"@context":"http://schema.org/","@type":"Physician","name":"Clxc3xa9ment TURMEAU","medicalSpecialty":"Ostxc3xa9opathe","legalName":"Monsieur Clxc3xa9ment TURMEAU","url":"/osteopathe/la-chapelle-sur-erdre/clement-turmeau","address":{"@type":"PostalAddress","name":"","streetAddress":"15 Rue Guillaume Grootaers","postalCode":"44300","addressLocality":"Nantes"},"paymentAccepted":"Cash, Check, Credit card"},{"@context":"http://schema.org/","@type":"Physician","name":"Angela NOCERA","medicalSpecialty":"Ostxc3xa9opathe","legalName":"","url":"/osteopathe/ermont/angela-nocera","address":{"@type":"PostalAddress","name":"Cabinet mxc3xa9dical","streetAddress":"5 Place des Marchands Laboureurs","postalCode":"95120","addressLocality":"Ermont"},"paymentAccepted":"Cash, Check"},{"@context":"http://schema.org/","@type":"Physician","name":"Mathilde Laviec","medicalSpecialty":"Ostxc3xa9opathe","legalName":null,"url":"/osteopathe/caen/mathilde-laviec","address":{"@type":"PostalAddress","name":"","streetAddress":"17 Rue Jean Romain","postalCode":"14000","addressLocality":"Caen"},"paymentAccepted":"Cash, Check, Credit card"},{"@context":"http://schema.org/","@type":"Physician","name":"Sebastien DITCHARLES","medicalSpecialty":"Ostxc3xa9opathe","legalName":null,"url":"/osteopathe/le-plessis-robinson/sebastien-ditcharles","address":{"@type":"PostalAddress","name":"","streetAddress":"10 Rue de la Mairie","postalCode":"92350","addressLocality":"Le Plessis-Robinson"},"paymentAccepted":"Cash, Check"},{"@context":"http://schema.org/","@type":"Physician","name":"Katiana Benito Velasco","medicalSpecialty":"Ostxc3xa9opathe","legalName":null,"url":"/osteopathe/saint-vincent-de-tyrosse/katiana-benito-velasco","address":{"@type":"PostalAddress","name":"Pxc3xb4le thxc3xa9rapie","streetAddress":"205 Avenue de Terreblanque","postalCode":"40230","addressLocality":"Saint-Vincent-de-Tyrosse"},"paymentAccepted":"Cash, Check, Credit card"},{"@context":"http://schema.org/","@type":"Physician","name":"Fanny MOLLARD","medicalSpecialty":"Ostxc3xa9opathe","legalName":null,"url":"/osteopathe/saint-gervais-les-bains/fanny-mollard-saint-gervais-les-bains","address":{"@type":"PostalAddress","name":"Maison Mxc3xa9dicale de Combloux","streetAddress":"81 Route de Sallanches","postalCode":"74920","addressLocality":"Combloux"},"paymentAccepted":""},{"@context":"http://schema.org/","@type":"Physician","name":"Jean-Baptiste CRESSENT","medicalSpecialty":"Ostxc3xa9opathe","legalName":"Jean-Baptiste Cressent","url":"/osteopathe/montferrier-sur-lez/jean-baptiste-cressent","address":{"@type":"PostalAddress","name":"Maison Mxc3xa9dicale Languedoc Mutualitxc3xa9","streetAddress":"128 Rue du Caducxc3xa9e","postalCode":"34090","addressLocality":"Montpellier"},"paymentAccepted":"Cash, Check"},{"@context":"http://schema.org/","@type":"Physician","name":"Jonathan Sebag","medicalSpecialty":"Ostxc3xa9opathe","legalName":null,"url":"/osteopathe/nice/jonathan-sebag","address":{"@type":"PostalAddress","name":"Centre mxc3xa9dical "Consultations 7/7" le port/Est","streetAddress":"24B Rue Smolett","postalCode":"06300","addressLocality":"Nice"},"paymentAccepted":""},{"@context":"http://schema.org/","@type":"Physician","name":"Sophie BESSIS","medicalSpecialty":"Ostxc3xa9opathe","legalName":null,"url":"/osteopathe/nerac/sophie-bessis","address":{"@type":"PostalAddress","name":null,"streetAddress":"4 Rue Georges Caillau","postalCode":"47600","addressLocality":"Nxc3xa9rac"},"paymentAccepted":"Cash, Check"},{"@context":"http://schema.org/","@type":"Physician","name":"Damien Ithursarry","medicalSpecialty":"Ostxc3xa9opathe","legalName":null,"url":"/osteopathe/boucau/damien-ithursarry","address":{"@type":"PostalAddress","name":"","streetAddress":"7 Rue Pierre Lacouture","postalCode":"64340","addressLocality":"Boucau"},"paymentAccepted":"Cash, Check, Credit card"},{"@context":"http://schema.org/","@type":"Physician","name":"Florian Monfroy","medicalSpecialty":"Ostxc3xa9opathe","legalName":null,"url":"/osteopathe/fleury-les-aubrais/florian-monfroy","address":{"@type":"PostalAddress","name":"","streetAddress":"2 Rue Hoche","postalCode":"45400","addressLocality":"Fleury-les-Aubrais"},"paymentAccepted":"Cash, Check, Credit card"},{"@context":"http://schema.org/","@type":"Physician","name":"Ciro CONFESSORE","medicalSpecialty":"Mxc3xa9decin gxc3xa9nxc3xa9raliste","legalName":null,"url":"/medecin-generaliste/annemasse/ciro-confessore","address":{"@type":"PostalAddress","name":"Cabinet du docteur Confessore","streetAddress":"3 Rue des Frxc3xa8res Tassile","postalCode":"74100","addressLocality":"Annemasse"},"paymentAccepted":"Cash, Check, Credit card"}]